rpgpack/__init__.py
rpgpack/commands/__init__.py
rpgpack/commands/abstract/__init__.py
rpgpack/commands/abstract/dndbattletarget.py
rpgpack/commands/dice.py
rpgpack/commands/dndactive.py
rpgpack/commands/dndactivebattle.py
rpgpack/commands/dndaddunit.py
rpgpack/commands/dnddamage.py
rpgpack/commands/dnddeathsave.py
rpgpack/commands/dndedit.py
rpgpack/commands/dndextra.py
rpgpack/commands/dndheal.py
rpgpack/commands/dndinfo.py
rpgpack/commands/dnditem.py
rpgpack/commands/dndjoinbattle.py
rpgpack/commands/dndnew.py
rpgpack/commands/dndnewbattle.py
rpgpack/commands/dndroll.py
rpgpack/commands/dndspell.py
rpgpack/commands/dndstatus.py
rpgpack/commands/roll.py
rpgpack/commands/testfaction.py
rpgpack/commands/testhealth.py
rpgpack/events/__init__.py
rpgpack/stars/__init__.py
rpgpack/stars/api_dnd_character.py
rpgpack/tables/__init__.py
rpgpack/tables/dndactivebattle.py
rpgpack/tables/dndactivecharacters.py
rpgpack/tables/dndbattle.py
rpgpack/tables/dndbattleunit.py
rpgpack/tables/dndcharacters.py
rpgpack/types/__init__.py
rpgpack/types/dndproficiencytype.py
rpgpack/types/faction.py
rpgpack/types/health.py
rpgpack/utils/__init__.py
rpgpack/utils/getactivebattle.py
rpgpack/utils/getactivechar.py
rpgpack/utils/getinterfacedata.py
rpgpack/utils/gettargets.py
rpgpack/utils/parse5etoolsentry.py
rpgpack/version.py
rpgpack-5.9.2.dist-info/LICENSE.txt
rpgpack-5.9.2.dist-info/WHEEL
rpgpack-5.9.2.dist-info/METADATA
rpgpack-5.9.2.dist-info/RECORD
