Metadata-Version: 2.1
Name: rpgpack
Version: 5.9.2
Summary: A Dungeons & Dragons utilities pack for Royalnet
Home-page: https://github.com/Steffo99/rpgpack
License: AGPL-3.0-or-later
Author: Stefano Pigozzi
Author-email: ste.pigozzi@gmail.com
Requires-Python: >=3.8,<4.0
Classifier: Development Status :: 4 - Beta
Classifier: License :: OSI Approved :: GNU Affero General Public License v3 or later (AGPLv3+)
Classifier: Operating System :: OS Independent
Classifier: Programming Language :: Python :: 3
Classifier: Programming Language :: Python :: 3.8
Requires-Dist: aiohttp (>=3.5,<4.0)
Requires-Dist: bcrypt (==3.2.0)
Requires-Dist: dice (>=2.4.2,<3.0.0)
Requires-Dist: royalnet[alchemy_easy,herald,telegram,discord,constellation] (>=5.11.12,<5.12.0)
Requires-Dist: sortedcontainers (>=2.1.0,<3.0.0)
Requires-Dist: sqlalchemy (==1.3.19)
